morecopy/__init__.py
morecopy/copiers.py
morecopy/copy.py
morecopy/py.typed
morecopy-0.4.0.dist-info/LICENSE
morecopy-0.4.0.dist-info/METADATA
morecopy-0.4.0.dist-info/WHEEL
morecopy-0.4.0.dist-info/RECORD
