Metadata-Version: 2.1
Name: morecopy
Version: 0.4.0
Summary: Copy even immutable objects as much as possible
Home-page: https://github.com/astropenguin/morecopy/
License: MIT
Keywords: copy,deepcopy
Author: Akio Taniguchi
Author-email: taniguchi@a.phys.nagoya-u.ac.jp
Requires-Python: >=3.8,<3.13
Classifier: License :: OSI Approved :: MIT License
Classifier: Programming Language :: Python :: 3
Classifier: Programming Language :: Python :: 3.8
Classifier: Programming Language :: Python :: 3.9
Classifier: Programming Language :: Python :: 3.10
Classifier: Programming Language :: Python :: 3.11
